adt/__init__.py
adt/examples.py
adt-0.0.2.dist-info/METADATA
adt-0.0.2.dist-info/WHEEL
adt-0.0.2.dist-info/top_level.txt
adt-0.0.2.dist-info/RECORD
