Metadata-Version: 2.2
Name: adt
Version: 0.0.2
Summary: Algebraic Data Types in Python
Author-email: Lewis Gaul <lewis.gaul@gmail.com>
License: MIT
Project-URL: Homepage, https://github.com/LewisGaul/python_adt/
Project-URL: Issues, https://github.com/LewisGaul/python_adt/issues/
Project-URL: Documentation, https://adt.readthedocs.io/
Classifier: Programming Language :: Python :: 3
Classifier: Development Status :: 2 - Pre-Alpha
Classifier: License :: OSI Approved :: MIT License
Classifier: Operating System :: OS Independent
Classifier: Intended Audience :: Developers
Requires-Python: >=3.9
